chord123
