Metadata-Version: 1.1
Name: Chord123
Version: 0.25
Summary: A command line script to translate a .docx of number-system chords to a specified key
Home-page: https://github.com/callistusystan/Chord123
Author: Callistus Tan
Author-email: callistusystan@example.com
License: MIT
Download-URL: https://github.com/callistusystan/Chord123/archive/0.25.tar.gz
Keywords: music,translate,chords,numbers
Platform: UNKNOWN
